comdirect_api/__init__.py
comdirect_api/comdirect_client.py
comdirect_api/auth/__init__.py
comdirect_api/auth/auth_service.py
comdirect_api/auth/comdirect_auth.py
comdirect_api/service/__init__.py
comdirect_api/service/account_service.py
comdirect_api/service/depot_service.py
comdirect_api/service/document_service.py
comdirect_api/service/instrument_service.py
comdirect_api/service/order_service.py
comdirect_api/service/report_service.py
comdirect_api_simple-0.0.15.dist-info/LICENSE
comdirect_api_simple-0.0.15.dist-info/METADATA
comdirect_api_simple-0.0.15.dist-info/WHEEL
comdirect_api_simple-0.0.15.dist-info/top_level.txt
comdirect_api_simple-0.0.15.dist-info/RECORD
