Metadata-Version: 2.1
Name: comdirect-api-simple
Version: 0.0.15
Summary: A package for read operations for the comdirect API
Home-page: https://github.com/alex-kn/comdirect-api-simple
Author: Alexander Knittel
Author-email: alx.kntl@gmail.com
License: UNKNOWN
Platform: UNKNOWN
Classifier: Programming Language :: Python :: 3
Classifier: License :: OSI Approved :: MIT License
Classifier: Operating System :: OS Independent
Requires-Python: >=3.6
Requires-Dist: requests
